DDF5Client.py-0.1.1.dist-info/DESCRIPTION.rst
DDF5Client.py-0.1.1.dist-info/METADATA
DDF5Client.py-0.1.1.dist-info/RECORD
DDF5Client.py-0.1.1.dist-info/WHEEL
DDF5Client.py-0.1.1.dist-info/metadata.json
DDF5Client.py-0.1.1.dist-info/top_level.txt
dimensiondata/__init__.py
dimensiondata/F5/__init__.py
dimensiondata/F5/base_client.py
dimensiondata/F5/client.py
