Metadata-Version: 2.0
Name: DDF5Client.py
Version: 0.1.1
Summary: F5 rest api client
Home-page: https://www.dimensiondata.com/
Author: Larry Lui
Author-email: lawrence.lui@itaas.dimensiondata.com
License: UNKNOWN
Platform: UNKNOWN
Requires-Dist: requests (>=2.8)
Requires-Dist: urllib3
